<?xml version="1.0" encoding="UTF-8"?>
<GenRun Id="impl_1" LaunchPart="xc7a100tcsg324-1" LaunchTime="1725415358">
  <File Type="ROUTE-PWR" Name="Header_power_routed.rpt"/>
  <File Type="PA-TCL" Name="Header.tcl"/>
  <File Type="BITSTR-MMI" Name="Header.mmi"/>
  <File Type="OPT-METHODOLOGY-DRC" Name="Header_methodology_drc_opted.rpt"/>
  <File Type="INIT-TIMING" Name="Header_timing_summary_init.rpt"/>
  <File Type="ROUTE-PWR-SUM" Name="Header_power_summary_routed.pb"/>
  <File Type="REPORTS-TCL" Name="Header_reports.tcl"/>
  <File Type="OPT-TIMING" Name="Header_timing_summary_opted.rpt"/>
  <File Type="OPT-DCP" Name="Header_opt.dcp"/>
  <File Type="OPT-DRC" Name="Header_drc_opted.rpt"/>
  <File Type="OPT-HWDEF" Name="Header.hwdef"/>
  <File Type="PWROPT-DCP" Name="Header_pwropt.dcp"/>
  <File Type="PWROPT-DRC" Name="Header_drc_pwropted.rpt"/>
  <File Type="PWROPT-TIMING" Name="Header_timing_summary_pwropted.rpt"/>
  <File Type="PLACE-DCP" Name="Header_placed.dcp"/>
  <File Type="PLACE-IO" Name="Header_io_placed.rpt"/>
  <File Type="PLACE-CLK" Name="Header_clock_utilization_placed.rpt"/>
  <File Type="PLACE-UTIL" Name="Header_utilization_placed.rpt"/>
  <File Type="PLACE-UTIL-PB" Name="Header_utilization_placed.pb"/>
  <File Type="PLACE-CTRL" Name="Header_control_sets_placed.rpt"/>
  <File Type="PLACE-SIMILARITY" Name="Header_incremental_reuse_placed.rpt"/>
  <File Type="PLACE-PRE-SIMILARITY" Name="Header_incremental_reuse_pre_placed.rpt"/>
  <File Type="BG-BIN" Name="Header.bin"/>
  <File Type="PLACE-TIMING" Name="Header_timing_summary_placed.rpt"/>
  <File Type="POSTPLACE-PWROPT-DCP" Name="Header_postplace_pwropt.dcp"/>
  <File Type="BITSTR-MSK" Name="Header.msk"/>
  <File Type="POSTPLACE-PWROPT-TIMING" Name="Header_timing_summary_postplace_pwropted.rpt"/>
  <File Type="PHYSOPT-DCP" Name="Header_physopt.dcp"/>
  <File Type="PHYSOPT-DRC" Name="Header_drc_physopted.rpt"/>
  <File Type="BITSTR-RBT" Name="Header.rbt"/>
  <File Type="PHYSOPT-TIMING" Name="Header_timing_summary_physopted.rpt"/>
  <File Type="ROUTE-ERROR-DCP" Name="Header_routed_error.dcp"/>
  <File Type="ROUTE-DCP" Name="Header_routed.dcp"/>
  <File Type="ROUTE-BLACKBOX-DCP" Name="Header_routed_bb.dcp"/>
  <File Type="ROUTE-DRC" Name="Header_drc_routed.rpt"/>
  <File Type="ROUTE-DRC-PB" Name="Header_drc_routed.pb"/>
  <File Type="ROUTE-DRC-RPX" Name="Header_drc_routed.rpx"/>
  <File Type="ROUTE-METHODOLOGY-DRC" Name="Header_methodology_drc_routed.rpt"/>
  <File Type="ROUTE-METHODOLOGY-DRC-RPX" Name="Header_methodology_drc_routed.rpx"/>
  <File Type="ROUTE-METHODOLOGY-DRC-PB" Name="Header_methodology_drc_routed.pb"/>
  <File Type="ROUTE-PWR-RPX" Name="Header_power_routed.rpx"/>
  <File Type="ROUTE-STATUS" Name="Header_route_status.rpt"/>
  <File Type="ROUTE-STATUS-PB" Name="Header_route_status.pb"/>
  <File Type="ROUTE-TIMINGSUMMARY" Name="Header_timing_summary_routed.rpt"/>
  <File Type="ROUTE-TIMING-PB" Name="Header_timing_summary_routed.pb"/>
  <File Type="ROUTE-TIMING-RPX" Name="Header_timing_summary_routed.rpx"/>
  <File Type="ROUTE-SIMILARITY" Name="Header_incremental_reuse_routed.rpt"/>
  <File Type="ROUTE-CLK" Name="Header_clock_utilization_routed.rpt"/>
  <File Type="ROUTE-BUS-SKEW" Name="Header_bus_skew_routed.rpt"/>
  <File Type="ROUTE-BUS-SKEW-PB" Name="Header_bus_skew_routed.pb"/>
  <File Type="ROUTE-BUS-SKEW-RPX" Name="Header_bus_skew_routed.rpx"/>
  <File Type="POSTROUTE-PHYSOPT-DCP" Name="Header_postroute_physopt.dcp"/>
  <File Type="POSTROUTE-PHYSOPT-BLACKBOX-DCP" Name="Header_postroute_physopt_bb.dcp"/>
  <File Type="POSTROUTE-PHYSOPT-TIMING" Name="Header_timing_summary_postroute_physopted.rpt"/>
  <File Type="POSTROUTE-PHYSOPT-TIMING-PB" Name="Header_timing_summary_postroute_physopted.pb"/>
  <File Type="POSTROUTE-PHYSOPT-TIMING-RPX" Name="Header_timing_summary_postroute_physopted.rpx"/>
  <File Type="POSTROUTE-PHYSOPT-BUS-SKEW" Name="Header_bus_skew_postroute_physopted.rpt"/>
  <File Type="BG-BIT" Name="Header.bit"/>
  <File Type="POSTROUTE-PHYSOPT-BUS-SKEW-PB" Name="Header_bus_skew_postroute_physopted.pb"/>
  <File Type="POSTROUTE-PHYSOPT-BUS-SKEW-RPX" Name="Header_bus_skew_postroute_physopted.rpx"/>
  <File Type="BITSTR-NKY" Name="Header.nky"/>
  <File Type="BITSTR-BMM" Name="Header_bd.bmm"/>
  <File Type="PDI-FILE" Name="Header.pdi"/>
  <File Type="RCFI_FILE" Name="Header.rcfi"/>
  <File Type="CFI_FILE" Name="Header.cfi"/>
  <File Type="RNPI_FILE" Name="Header.rnpi"/>
  <File Type="NPI_FILE" Name="Header.npi"/>
  <File Type="RBD_FILE" Name="Header.rbd"/>
  <File Type="BITSTR-LTX" Name="debug_nets.ltx"/>
  <File Type="BITSTR-LTX" Name="Header.ltx"/>
  <File Type="BITSTR-SYSDEF" Name="Header.sysdef"/>
  <File Type="BG-BGN" Name="Header.bgn"/>
  <File Type="BG-DRC" Name="Header.drc"/>
  <File Type="RDI-RDI" Name="Header.vdi"/>
  <File Type="WBT-USG" Name="usage_statistics_webtalk.html"/>
  <File Type="ROUTE-RQS" Name="Header_routed.rqs"/>
  <File Type="POSTROUTE-PHYSOPT-RQS" Name="Header_postroute_physopted.rqs"/>
  <File Type="ROUTE-RQS-RPT" Name="route_report_qor_suggestions_0.rpt"/>
  <File Type="POSTROUTE-PHYSOPT-RQS-RPT" Name="postroute_physopt_report_qor_suggestions_0.rpt"/>
  <FileSet Name="sources" Type="DesignSrcs" RelSrcDir="$PSRCDIR/sources_1" RelGenDir="$PGENDIR/sources_1">
    <Filter Type="Srcs"/>
    <File Path="$PSRCDIR/sources_1/new/clockDivider.vhd">
      <FileInfo>
        <Attr Name="UsedIn" Val="synthesis"/>
        <Attr Name="UsedIn" Val="simulation"/>
      </FileInfo>
    </File>
    <File Path="$PSRCDIR/sources_1/new/counter.vhd">
      <FileInfo>
        <Attr Name="UsedIn" Val="synthesis"/>
        <Attr Name="UsedIn" Val="simulation"/>
      </FileInfo>
    </File>
    <File Path="$PSRCDIR/sources_1/new/demux.vhd">
      <FileInfo>
        <Attr Name="UsedIn" Val="synthesis"/>
        <Attr Name="UsedIn" Val="simulation"/>
      </FileInfo>
    </File>
    <File Path="$PSRCDIR/sources_1/new/sub.vhd">
      <FileInfo>
        <Attr Name="UsedIn" Val="synthesis"/>
        <Attr Name="UsedIn" Val="simulation"/>
      </FileInfo>
    </File>
    <File Path="$PSRCDIR/sources_1/new/mux.vhd">
      <FileInfo>
        <Attr Name="UsedIn" Val="synthesis"/>
        <Attr Name="UsedIn" Val="simulation"/>
      </FileInfo>
    </File>
    <File Path="$PSRCDIR/sources_1/new/hex_to_ssd.vhd">
      <FileInfo>
        <Attr Name="UsedIn" Val="synthesis"/>
        <Attr Name="UsedIn" Val="simulation"/>
      </FileInfo>
    </File>
    <File Path="$PSRCDIR/sources_1/new/head.vhd">
      <FileInfo>
        <Attr Name="UsedIn" Val="synthesis"/>
        <Attr Name="UsedIn" Val="simulation"/>
      </FileInfo>
    </File>
    <File Path="$PSRCDIR/sources_1/new/full_adder.vhd">
      <FileInfo>
        <Attr Name="AutoDisabled" Val="1"/>
        <Attr Name="UsedIn" Val="synthesis"/>
        <Attr Name="UsedIn" Val="simulation"/>
      </FileInfo>
    </File>
    <File Path="$PSRCDIR/sources_1/new/addsub_4bit.vhd">
      <FileInfo>
        <Attr Name="AutoDisabled" Val="1"/>
        <Attr Name="UsedIn" Val="synthesis"/>
        <Attr Name="UsedIn" Val="simulation"/>
      </FileInfo>
    </File>
    <File Path="$PSRCDIR/sources_1/new/onedigitBCDadder.vhd">
      <FileInfo>
        <Attr Name="AutoDisabled" Val="1"/>
        <Attr Name="UsedIn" Val="synthesis"/>
        <Attr Name="UsedIn" Val="simulation"/>
      </FileInfo>
    </File>
    <File Path="$PSRCDIR/sources_1/new/subby.vhd">
      <FileInfo>
        <Attr Name="AutoDisabled" Val="1"/>
        <Attr Name="UsedIn" Val="synthesis"/>
        <Attr Name="UsedIn" Val="simulation"/>
      </FileInfo>
    </File>
    <File Path="$PSRCDIR/sources_1/new/twodigitadder.vhd">
      <FileInfo>
        <Attr Name="AutoDisabled" Val="1"/>
        <Attr Name="UsedIn" Val="synthesis"/>
        <Attr Name="UsedIn" Val="simulation"/>
      </FileInfo>
    </File>
    <File Path="$PSRCDIR/sources_1/new/BCD_ADDER.vhd">
      <FileInfo>
        <Attr Name="AutoDisabled" Val="1"/>
        <Attr Name="UsedIn" Val="synthesis"/>
        <Attr Name="UsedIn" Val="simulation"/>
      </FileInfo>
    </File>
    <File Path="$PSRCDIR/sources_1/new/four.vhd">
      <FileInfo>
        <Attr Name="AutoDisabled" Val="1"/>
        <Attr Name="UsedIn" Val="synthesis"/>
        <Attr Name="UsedIn" Val="simulation"/>
      </FileInfo>
    </File>
    <File Path="$PSRCDIR/sources_1/new/onedigitaddandsubtract.vhd">
      <FileInfo>
        <Attr Name="AutoDisabled" Val="1"/>
        <Attr Name="UsedIn" Val="synthesis"/>
        <Attr Name="UsedIn" Val="simulation"/>
      </FileInfo>
    </File>
    <Config>
      <Option Name="DesignMode" Val="RTL"/>
      <Option Name="TopModule" Val="Header"/>
    </Config>
  </FileSet>
  <FileSet Name="constrs_in" Type="Constrs" RelSrcDir="$PSRCDIR/constrs_1">
    <Filter Type="Constrs"/>
    <File Path="$PSRCDIR/constrs_1/new/constraints.xdc">
      <FileInfo>
        <Attr Name="UsedIn" Val="synthesis"/>
        <Attr Name="UsedIn" Val="implementation"/>
      </FileInfo>
    </File>
    <Config>
      <Option Name="ConstrsType" Val="XDC"/>
    </Config>
  </FileSet>
  <FileSet Name="utils" Type="Utils" RelSrcDir="$PSRCDIR/utils_1">
    <Filter Type="Utils"/>
    <File Path="$PSRCDIR/utils_1/imports/synth_1/onedigitBCDadder.dcp">
      <FileInfo>
        <Attr Name="UsedIn" Val="synthesis"/>
        <Attr Name="UsedIn" Val="implementation"/>
        <Attr Name="UsedInSteps" Val="synth_1"/>
        <Attr Name="AutoDcp" Val="1"/>
      </FileInfo>
    </File>
    <Config>
      <Option Name="TopAutoSet" Val="TRUE"/>
    </Config>
  </FileSet>
  <Strategy Version="1" Minor="2">
    <StratHandle Name="Vivado Implementation Defaults" Flow="Vivado Implementation 2022"/>
    <Step Id="init_design"/>
    <Step Id="opt_design"/>
    <Step Id="power_opt_design"/>
    <Step Id="place_design"/>
    <Step Id="post_place_power_opt_design"/>
    <Step Id="phys_opt_design"/>
    <Step Id="route_design"/>
    <Step Id="post_route_phys_opt_design"/>
    <Step Id="write_bitstream"/>
  </Strategy>
</GenRun>
